{
  "runs": [
    {
      "timestamp": "2026-04-24T09:24:42.008562",
      "python_version": "3.14.4",
      "results": {
        "CRUDPerformanceTest": {
          "create": {
            "iterations": 100,
            "min_ms": 1.6604,
            "max_ms": 3.274,
            "avg_ms": 1.7895,
            "median_ms": 1.7653
          },
          "delete": {
            "iterations": 100,
            "min_ms": 1.8051,
            "max_ms": 2.8798,
            "avg_ms": 1.9261,
            "median_ms": 1.9011
          },
          "list": {
            "iterations": 100,
            "min_ms": 3.0045,
            "max_ms": 3.8938,
            "avg_ms": 3.2391,
            "median_ms": 3.2279
          },
          "retrieve": {
            "iterations": 100,
            "min_ms": 1.1663,
            "max_ms": 1.8768,
            "avg_ms": 1.2688,
            "median_ms": 1.249
          },
          "update": {
            "iterations": 100,
            "min_ms": 2.1789,
            "max_ms": 2.7579,
            "avg_ms": 2.3649,
            "median_ms": 2.3525
          }
        },
        "FilterPerformanceTest": {
          "boolean_filter": {
            "iterations": 100,
            "min_ms": 3.235,
            "max_ms": 4.3318,
            "avg_ms": 3.4363,
            "median_ms": 3.4209
          },
          "combined_filters": {
            "iterations": 100,
            "min_ms": 1.9217,
            "max_ms": 35.299,
            "avg_ms": 2.4548,
            "median_ms": 2.0738
          },
          "icontains_filter": {
            "iterations": 100,
            "min_ms": 1.7398,
            "max_ms": 2.5889,
            "avg_ms": 1.8848,
            "median_ms": 1.8622
          },
          "match_case_filter": {
            "iterations": 100,
            "min_ms": 2.4242,
            "max_ms": 3.5739,
            "avg_ms": 2.579,
            "median_ms": 2.5378
          },
          "numeric_filter": {
            "iterations": 100,
            "min_ms": 1.4618,
            "max_ms": 1.8716,
            "avg_ms": 1.5576,
            "median_ms": 1.5436
          },
          "relation_filter": {
            "iterations": 100,
            "min_ms": 16.7596,
            "max_ms": 21.9243,
            "avg_ms": 17.4107,
            "median_ms": 17.3672
          }
        },
        "LargeListPerformanceTest": {
          "list_1000_page100": {
            "iterations": 100,
            "min_ms": 2.8438,
            "max_ms": 3.9242,
            "avg_ms": 3.0779,
            "median_ms": 3.0417
          },
          "list_1000_page20": {
            "iterations": 100,
            "min_ms": 1.6311,
            "max_ms": 2.1697,
            "avg_ms": 1.7285,
            "median_ms": 1.7093
          }
        },
        "MultiFKPerformanceTest": {
          "bulk_create_50x3fk": {
            "iterations": 10,
            "min_ms": 84.4311,
            "max_ms": 103.6308,
            "avg_ms": 89.1768,
            "median_ms": 86.3113
          },
          "create_3fk": {
            "iterations": 50,
            "min_ms": 2.7946,
            "max_ms": 4.0603,
            "avg_ms": 2.9747,
            "median_ms": 2.9277
          }
        },
        "SchemaGenerationPerformanceTest": {
          "meta_serializer_schema_generation": {
            "iterations": 100,
            "min_ms": 0.0006,
            "max_ms": 3.4764,
            "avg_ms": 0.0354,
            "median_ms": 0.0006
          },
          "model_serializer_schema_generation": {
            "iterations": 100,
            "min_ms": 0.0012,
            "max_ms": 0.0118,
            "avg_ms": 0.0015,
            "median_ms": 0.0013
          },
          "schema_with_relations": {
            "iterations": 100,
            "min_ms": 0.0004,
            "max_ms": 1.9531,
            "avg_ms": 0.02,
            "median_ms": 0.0004
          },
          "schema_with_validators": {
            "iterations": 100,
            "min_ms": 0.0006,
            "max_ms": 3.8938,
            "avg_ms": 0.0396,
            "median_ms": 0.0006
          }
        },
        "SerializationPerformanceTest": {
          "bulk_serialization_100": {
            "iterations": 50,
            "min_ms": 1.2647,
            "max_ms": 3.0366,
            "avg_ms": 1.3564,
            "median_ms": 1.3124
          },
          "bulk_serialization_500": {
            "iterations": 50,
            "min_ms": 4.0736,
            "max_ms": 8.5413,
            "avg_ms": 4.306,
            "median_ms": 4.1953
          },
          "input_parsing": {
            "iterations": 100,
            "min_ms": 0.56,
            "max_ms": 0.8086,
            "avg_ms": 0.6068,
            "median_ms": 0.6004
          },
          "relation_serialization": {
            "iterations": 100,
            "min_ms": 0.5542,
            "max_ms": 0.8191,
            "avg_ms": 0.6141,
            "median_ms": 0.6079
          },
          "single_object_serialization": {
            "iterations": 100,
            "min_ms": 0.5378,
            "max_ms": 0.8858,
            "avg_ms": 0.5875,
            "median_ms": 0.5787
          }
        }
      }
    }
  ]
}